roofdata/__init__.py
roofdata/check_format.py
roofdata/extract_roof_data.py
roofdata/roofdataextractor.py
roofdata/xml_to_json.py
roofdataextractor-0.1.4.dist-info/LICENSE
roofdataextractor-0.1.4.dist-info/METADATA
roofdataextractor-0.1.4.dist-info/WHEEL
roofdataextractor-0.1.4.dist-info/top_level.txt
roofdataextractor-0.1.4.dist-info/RECORD
