Metadata-Version: 2.1
Name: roofdataextractor
Version: 0.1.4
Summary: A package to extract certain points and data about from xml file
Home-page: https://github.com/arnasvid/PSI-2022-GR3-Area1
Author: V.Straigis, A. Kuznecovas, A.Vidziunas, T.Jefimovas, M. Neseckas
Author-email: author@example.com
Project-URL: Bug Tracker, https://github.com/arnasvid/PSI-2022-GR3-Area1/issues
Classifier: Programming Language :: Python :: 3
Classifier: License :: OSI Approved :: MIT License
Classifier: Operating System :: OS Independent
Requires-Python: >=3.6
License-File: LICENSE
